gpt_cost_estimator/__init__.py
gpt_cost_estimator/estimator.py
gpt_cost_estimator/utils.py
gpt_cost_estimator-0.7.dist-info/LICENSE
gpt_cost_estimator-0.7.dist-info/METADATA
gpt_cost_estimator-0.7.dist-info/WHEEL
gpt_cost_estimator-0.7.dist-info/top_level.txt
gpt_cost_estimator-0.7.dist-info/RECORD
