Metadata-Version: 2.1
Name: gpt_cost_estimator
Version: 0.7
Summary: A cost estimator for OpenAI API calls in tqdm loops.
Home-page: https://github.com/michaelachmann/gpt-cost-estimator/
Author: Michael Achmann
Author-email: michael.achmann@informatik.uni-regensburg.de
License-File: LICENSE
Requires-Dist: tiktoken
Requires-Dist: openai
Requires-Dist: tqdm
Requires-Dist: lorem_text
